heavykeeper-0.2.2.dist-info/METADATA
heavykeeper-0.2.2.dist-info/WHEEL
heavykeeper-0.2.2.dist-info/licenses/LICENSE
heavykeeper/__init__.py
heavykeeper/heavykeeper.cpython-311-x86_64-linux-gnu.so
heavykeeper-0.2.2.dist-info/RECORD
