Metadata-Version: 2.4
Name: heavykeeper
Version: 0.2.2
Classifier: Programming Language :: Python
Classifier: Programming Language :: Rust
Classifier: License :: OSI Approved :: MIT License
Classifier: Operating System :: OS Independent
Requires-Dist: pytest ; extra == 'test'
Provides-Extra: test
License-File: LICENSE
Summary: Python bindings for the HeavyKeeper algorithm implemented in Rust
Author: Patrick McGleenon
License: MIT
Requires-Python: >=3.11
Project-URL: Homepage, https://github.com/pmcgleenon/heavykeeper-py
Project-URL: Repository, https://github.com/pmcgleenon/heavykeeper-py
Project-URL: Bug Reports, https://github.com/pmcgleenon/heavykeeper-py/issues
Project-URL: Source, https://github.com/pmcgleenon/heavykeeper-py
